py_ocpi/__init__.py
py_ocpi/main.py
py_ocpi/core/__init__.py
py_ocpi/core/adapter.py
py_ocpi/core/config.py
py_ocpi/core/crud.py
py_ocpi/core/data_types.py
py_ocpi/core/dependencies.py
py_ocpi/core/enums.py
py_ocpi/core/exceptions.py
py_ocpi/core/logs.py
py_ocpi/core/push.py
py_ocpi/core/schemas.py
py_ocpi/core/status.py
py_ocpi/core/utils.py
py_ocpi/core/authentication/__init__.py
py_ocpi/core/authentication/authenticator.py
py_ocpi/core/authentication/verifier.py
py_ocpi/core/endpoints/__init__.py
py_ocpi/core/endpoints/utils.py
py_ocpi/core/endpoints/v_2_1_1/__init__.py
py_ocpi/core/endpoints/v_2_1_1/cpo.py
py_ocpi/core/endpoints/v_2_1_1/emsp.py
py_ocpi/core/endpoints/v_2_1_1/utils.py
py_ocpi/core/endpoints/v_2_2_1/__init__.py
py_ocpi/core/endpoints/v_2_2_1/cpo.py
py_ocpi/core/endpoints/v_2_2_1/emsp.py
py_ocpi/core/endpoints/v_2_2_1/utils.py
py_ocpi/core/routers/__init__.py
py_ocpi/core/routers/v_2_1_1/__init__.py
py_ocpi/core/routers/v_2_2_1/__init__.py
py_ocpi/modules/__init__.py
py_ocpi/modules/cdrs/__init__.py
py_ocpi/modules/cdrs/v_2_1_1/enums.py
py_ocpi/modules/cdrs/v_2_1_1/schemas.py
py_ocpi/modules/cdrs/v_2_1_1/api/__init__.py
py_ocpi/modules/cdrs/v_2_1_1/api/cpo.py
py_ocpi/modules/cdrs/v_2_1_1/api/emsp.py
py_ocpi/modules/cdrs/v_2_2_1/enums.py
py_ocpi/modules/cdrs/v_2_2_1/schemas.py
py_ocpi/modules/cdrs/v_2_2_1/api/__init__.py
py_ocpi/modules/cdrs/v_2_2_1/api/cpo.py
py_ocpi/modules/cdrs/v_2_2_1/api/emsp.py
py_ocpi/modules/chargingprofiles/__init__.py
py_ocpi/modules/chargingprofiles/v_2_2_1/background_tasks.py
py_ocpi/modules/chargingprofiles/v_2_2_1/enums.py
py_ocpi/modules/chargingprofiles/v_2_2_1/schemas.py
py_ocpi/modules/chargingprofiles/v_2_2_1/api/__init__.py
py_ocpi/modules/chargingprofiles/v_2_2_1/api/cpo.py
py_ocpi/modules/chargingprofiles/v_2_2_1/api/emsp.py
py_ocpi/modules/commands/__init__.py
py_ocpi/modules/commands/v_2_1_1/enums.py
py_ocpi/modules/commands/v_2_1_1/schemas.py
py_ocpi/modules/commands/v_2_1_1/api/__init__.py
extrawest_ocpi-2025.7.16.dist-info/METADATA
extrawest_ocpi-2025.7.16.dist-info/WHEEL
extrawest_ocpi-2025.7.16.dist-info/licenses/LICENSE
extrawest_ocpi-2025.7.16.dist-info/RECORD
