Metadata-Version: 2.4
Name: extrawest_ocpi
Version: 2025.7.16
Summary: Python implementation of Open Charge Point Interface (OCPI) protocol based on fastapi.
Project-URL: Homepage, https://github.com/extrawest/extrawest_ocpi
Project-URL: Repository, https://github.com/extrawest/extrawest_ocpi
Author-email: Oleksandr Bozbei <oleksandr.bozbei@extrawest.com>
License: MIT
License-File: LICENSE
Requires-Python: >=3.10
Requires-Dist: fastapi==0.101.1
Requires-Dist: httpx==0.24.1
Requires-Dist: pydantic==1.10.12
